sudokuaspuzzle/auxiliary.py
sudokuaspuzzle/constants.py
sudokuaspuzzle/entrypoint.py
sudokuaspuzzle/gamepixbufs.py
sudokuaspuzzle/myapplication.py
sudokuaspuzzle/picker.py
sudokuaspuzzle/puzzle.py
sudokuaspuzzle/windowmain.py
sudokuaspuzzle/windowmain_base.py
sudokuaspuzzle/windowmain_statics.py
sudokuaspuzzle/windowoptions.py
sudokuaspuzzle/windowoptions_base.py
sudokuaspuzzle/windowoptions_statics.py
sudokuaspuzzle/windowpuzzle.py
sudokuaspuzzle/windowpuzzle_base.py
sudokuaspuzzle/windowpuzzle_statics.py
sudokuaspuzzle/icons/edit-clear.png
sudokuaspuzzle/icons/edit-delete.png
sudokuaspuzzle/icons/logo.png
sudokuaspuzzle/info/ARTISTS
sudokuaspuzzle/info/AUTHORS
sudokuaspuzzle/info/COMMENTS
sudokuaspuzzle/info/COPYRIGHT
sudokuaspuzzle/info/LICENSE
sudokuaspuzzle/info/TRANSLATORS
sudokuaspuzzle/localedir/org.kekbay.sudokuaspuzzleocp.pot
sudokuaspuzzle/localedir/el/LC_MESSAGES/org.kekbay.sudokuaspuzzleocp.mo
sudokuaspuzzle/localedir/el/LC_MESSAGES/org.kekbay.sudokuaspuzzleocp.po
sudokuaspuzzle/ui/windowmain.glade
sudokuaspuzzle/ui/windowoptions.glade
sudokuaspuzzle/ui/windowpuzzle.glade
sudokuaspuzzle-0.1.28.dist-info/LICENSE
sudokuaspuzzle-0.1.28.dist-info/METADATA
sudokuaspuzzle-0.1.28.dist-info/WHEEL
sudokuaspuzzle-0.1.28.dist-info/entry_points.txt
sudokuaspuzzle-0.1.28.dist-info/top_level.txt
sudokuaspuzzle-0.1.28.dist-info/RECORD
