Metadata-Version: 2.1
Name: sudokuaspuzzle
Version: 0.1.28
Summary: Customizable Sudoku
Home-page: http://gnu.kekbay.gr/sudokuaspuzzle/versions
Author: Ηλίας Ηλιάδης
Author-email: iliadis@kekbay.gr
License: GPLv3
Project-URL: Source, https://gitlab.com/xoristzatziki/sudokuaspuzzle
Platform: UNKNOWN
Classifier: Development Status :: 4 - Beta
Classifier: Environment :: X11 Applications :: GTK
Classifier: Intended Audience :: End Users/Desktop
Classifier: License :: OSI Approved :: GNU General Public License v3 or later (GPLv3+)
Classifier: Programming Language :: Python :: 3.6
Classifier: Topic :: Games/Entertainment :: Puzzle Games
